README
setup.py
SSHA512Hasher.egg-info/PKG-INFO
SSHA512Hasher.egg-info/SOURCES.txt
SSHA512Hasher.egg-info/dependency_links.txt
SSHA512Hasher.egg-info/top_level.txt
ssha512/__init__.py
ssha512/dov_ssha512.py
ssha512/ssha512.py